trythatagain/__init__.py
trythatagain/decorators.py
trythatagain/exc.py
trythatagain/waiters.py
trythatagain-0.1.3.dist-info/METADATA
trythatagain-0.1.3.dist-info/RECORD
trythatagain-0.1.3.dist-info/WHEEL
trythatagain-0.1.3.dist-info/top_level.txt
